fastmcp_email_server/__init__.py
fastmcp_email_server/__main__.py
fastmcp_email_server/email_config.py
fastmcp_email_server/receive_163.py
fastmcp_email_server/send_163.py
fastmcp_email_server/server.py
fastmcp_email_server-0.1.0.dist-info/METADATA
fastmcp_email_server-0.1.0.dist-info/WHEEL
fastmcp_email_server-0.1.0.dist-info/entry_points.txt
fastmcp_email_server-0.1.0.dist-info/top_level.txt
fastmcp_email_server-0.1.0.dist-info/RECORD
