Metadata-Version: 2.4
Name: fastmcp-email-server
Version: 0.1.0
Summary: FastMCP 邮件收发 MCP 服务器
Author: Cocktail_py
Requires-Python: >=3.10
Requires-Dist: beautifulsoup4
Requires-Dist: build>=1.3.0
Requires-Dist: mcp[cli]>=1.15.0
Requires-Dist: twine>=6.2.0
